asyncjobs/__init__.py
asyncjobs/basic.py
asyncjobs/decorated_work.py
asyncjobs/external_work.py
asyncjobs/logcontext.py
asyncjobs/logmux.py
asyncjobs/logmuxed_work.py
asyncjobs/plot_schedule.py
asyncjobs/polyfill.py
asyncjobs/signal_handling.py
asyncjobs/stream_mux.py
asyncjobs-0.5.5.dist-info/LICENSE
asyncjobs-0.5.5.dist-info/METADATA
asyncjobs-0.5.5.dist-info/WHEEL
asyncjobs-0.5.5.dist-info/top_level.txt
asyncjobs-0.5.5.dist-info/RECORD
