Metadata-Version: 2.1
Name: asyncjobs
Version: 0.5.5
Summary: Asynchronous job scheduler
Home-page: https://github.com/jherland/asyncjobs
Author: Johan Herland
Author-email: johan@herland.net
License: UNKNOWN
Keywords: async asyncio job scheduler
Platform: UNKNOWN
Classifier: Development Status :: 3 - Alpha
Classifier: Framework :: AsyncIO
Classifier: Intended Audience :: Developers
Classifier: Intended Audience :: System Administrators
Classifier: License :: OSI Approved :: MIT License
Classifier: Operating System :: OS Independent
Classifier: Programming Language :: Python :: 3
Classifier: Programming Language :: Python :: 3.6
Classifier: Programming Language :: Python :: 3.7
Classifier: Programming Language :: Python :: 3.8
Classifier: Programming Language :: Python :: 3.9
Classifier: Topic :: Software Development :: Build Tools
Classifier: Topic :: Software Development :: Libraries :: Python Modules
Classifier: Topic :: Utilities
Requires-Python: >=3.6
Provides-Extra: dev
Requires-Dist: black ; extra == 'dev'
Requires-Dist: flake8 ; extra == 'dev'
Requires-Dist: nox ; extra == 'dev'
Provides-Extra: dist
Requires-Dist: check-manifest ; extra == 'dist'
Requires-Dist: twine ; extra == 'dist'
Requires-Dist: wheel ; extra == 'dist'
Provides-Extra: plot
Requires-Dist: numpy ; extra == 'plot'
Requires-Dist: plotly ; extra == 'plot'
Provides-Extra: test
Requires-Dist: beautifulsoup4 ; extra == 'test'
Requires-Dist: pytest (>=5.4.0) ; extra == 'test'
Requires-Dist: pytest-asyncio ; extra == 'test'
Requires-Dist: requests ; extra == 'test'
